deezersdk/__init__.py
deezersdk/deezersdk.py
testing/__init__.py
testing/testing.py
deezersdk-0.17.dist-info/LICENSE
deezersdk-0.17.dist-info/METADATA
deezersdk-0.17.dist-info/WHEEL
deezersdk-0.17.dist-info/top_level.txt
deezersdk-0.17.dist-info/RECORD
