Metadata-Version: 2.1
Name: deezersdk
Version: 0.17
Summary: A python SDK for the Deezer API
Home-page: https://github.com/AlexisGomes/deezersdk
Author: Gomes Alexis
Author-email: alexis.gomes19@gmail.com
License: UNKNOWN
Platform: UNKNOWN
Classifier: Programming Language :: Python :: 3
Classifier: License :: OSI Approved :: MIT License
Classifier: Operating System :: OS Independent
